LICENSE.txt
MANIFEST.in
README.txt
setup.py
radomermbg/__init__.py
radomermbg/radomer.py
radomermbg.egg-info/PKG-INFO
radomermbg.egg-info/SOURCES.txt
radomermbg.egg-info/dependency_links.txt
radomermbg.egg-info/requires.txt
radomermbg.egg-info/top_level.txt