Metadata-Version: 2.1
Name: radomermbg
Version: 0.0.9
Summary: background removal
Home-page: 
Author: SARVESH,SRIDHARAN,PRIYANKA
Author-email: cvradome@gmail.com
License: MIT
Keywords: background,subtraction
Classifier: Development Status :: 4 - Beta
Classifier: Intended Audience :: Developers
Classifier: Topic :: Software Development :: Build Tools
Classifier: License :: OSI Approved :: MIT License
Classifier: Programming Language :: Python :: 3.7
License-File: LICENSE.txt
